{
    "titulo": "\"Evolução em Desenvolvimento\"",
    "noticia": "A Índia está diante de um momento crítico em sua política criptográfica. Com um volume de negócios de $5 trilhões movendo-se para fora do país, é hora de mudanças. A ausência de políticas claras e regulamentações eficazes está afetando a economia indiana e incentivando os investidores a buscarem oportunidades em outros mercados.\n\nFonte: Ambcrypto",
    "tempo": "09:58",
    "data": "22/01/2026",
    "slug": "evolução-em-desenvolvimento"
}