{
    "titulo": "\"Whiplash para traders de criptomoedas: $665 milhões em apostas com juros são liquidadas\"",
    "noticia": "A semana está começando com um tom agitado no mercado de criptomoedas. De acordo com o tracker de dados CoinGlass, nos últimos 24 horas, $655 milhões em apostas com juros foram liquidados. Essa liquidação coincide com os movimentos rápidos do presidente Trump em relação à compra de Gronelândia e ao impasse sobre novos impostos para países da UE.\n\nA falta de estabilidade no preço do Bitcoin está causando uma grande confusão entre os traders que usam juros para apostar no valor futuro do BTC. A situação é preocupante, pois essas liquidações podem ter um impacto significativo nos mercados.",
    "tempo": "05:04",
    "data": "22/01/2026",
    "slug": "whiplash-para-traders-de-criptomoedas-665-milhões-"
}