{
    "titulo": "\"Bitcoin Price Plummets to Lowest Level in Weeks\"",
    "noticia": "Aos ouvintes, o mercado de criptomoedas está experienciando uma alta volatilidade nos últimos dias e isso afetou diretamente o preço do Bitcoin. Segundo a informação obtida pela fonte CoinDesk, o Bitcoin caiu para seu nível mais baixo em semanas, alcançando US$ 87,263 na quarta-feira. Isso representa uma perda de aproximadamente 10% em relação ao seu valor há uma semana.\n\nA análise feita pelo trader Wealthmanager indica que o Bitcoin já havia perdido todos os seus ganhos de 2026 e brevemente caiu abaixo do seu valor inicial e ponto de controle (POC). Ele afirma que este nível é crítico para a manutenção da tendência ascendente nos próximos dias.\n\nAlém disso, o analista Crypto Jelle destacou uma estrutura de bandeira em forma de urso no gráfico diário do Bitcoin, o que sugere um alto risco de ruptura. Ele afirma que se o Bitcoin perder os níveis atuais novamente, os ursos estarão novamente no controle e podemos ver um \"free fall\" (queda livre) que poderia levar o preço a volta ao US$ 80,000.\n\nPor fim, o analista Crypto Bullet fez uma comparação entre a atual performance do Bitcoin e sua performance em 2022. Ele afirma que o Bitcoin está atualmente seguindo um padrão semelhante ao seu desempenho em 2022, que resultou em uma correção de mais de 40% seguida por uma \"dead cat bounce\" (pulso morto) e outra correção para novos baixos.",
    "tempo": "05:15",
    "data": "22/01/2026",
    "slug": "bitcoin-price-plummets-to-lowest-level-in-weeks"
}